xpipe_client/__init__.py
xpipe_client/clients.py
xpipe_client/exceptions.py
xpipe_client-0.1.26.dist-info/LICENSE
xpipe_client-0.1.26.dist-info/METADATA
xpipe_client-0.1.26.dist-info/WHEEL
xpipe_client-0.1.26.dist-info/RECORD
